{
  "annotations": {
    "list": [
      {
        "builtIn": 1,
        "datasource": {
          "type": "grafana",
          "uid": "-- Grafana --"
        },
        "enable": true,
        "hide": true,
        "iconColor": "rgba(0, 211, 255, 1)",
        "name": "Annotations & Alerts",
        "type": "dashboard"
      }
    ]
  },
  "editable": true,
  "fiscalYearStartMonth": 0,
  "graphTooltip": 0,
  "id": 4,
  "links": [],
  "panels": [
    {
      "datasource": {
        "uid": "fendaf7rut9moc"
      },
      "fieldConfig": {
        "defaults": {
          "color": {
            "mode": "thresholds"
          },
          "mappings": [],
          "thresholds": {
            "mode": "absolute",
            "steps": [
              {
                "color": "green"
              },
              {
                "color": "red",
                "value": 80
              }
            ]
          }
        },
        "overrides": []
      },
      "gridPos": {
        "h": 5,
        "w": 16,
        "x": 0,
        "y": 0
      },
      "id": 3,
      "options": {
        "minVizHeight": 75,
        "minVizWidth": 75,
        "orientation": "auto",
        "reduceOptions": {
          "calcs": [
            "lastNotNull"
          ],
          "fields": "",
          "values": false
        },
        "showThresholdLabels": false,
        "showThresholdMarkers": true,
        "sizing": "auto"
      },
      "pluginVersion": "12.0.1",
      "targets": [
        {
          "editorMode": "builder",
          "format": "table",
          "rawSql": "SELECT COUNT(id) FROM alarm_logs LIMIT 50 ",
          "refId": "A",
          "sql": {
            "columns": [
              {
                "name": "COUNT",
                "parameters": [
                  {
                    "name": "id",
                    "type": "functionParameter"
                  }
                ],
                "type": "function"
              }
            ],
            "groupBy": [
              {
                "property": {
                  "type": "string"
                },
                "type": "groupBy"
              }
            ],
            "limit": 50
          },
          "table": "alarm_logs"
        }
      ],
      "title": "COUNT",
      "type": "gauge"
    },
    {
      "datasource": {
        "type": "grafana-postgresql-datasource",
        "uid": "fendaf7rut9moc"
      },
      "fieldConfig": {
        "defaults": {
          "custom": {
            "align": "auto",
            "cellOptions": {
              "type": "auto"
            },
            "inspect": false
          },
          "mappings": [],
          "thresholds": {
            "mode": "absolute",
            "steps": [
              {
                "color": "green"
              },
              {
                "color": "red",
                "value": 80
              }
            ]
          }
        },
        "overrides": []
      },
      "gridPos": {
        "h": 8,
        "w": 16,
        "x": 0,
        "y": 5
      },
      "id": 2,
      "options": {
        "cellHeight": "sm",
        "footer": {
          "countRows": false,
          "fields": "",
          "reducer": [
            "sum"
          ],
          "show": false
        },
        "showHeader": true
      },
      "pluginVersion": "12.0.1",
      "targets": [
        {
          "datasource": {
            "type": "grafana-postgresql-datasource",
            "uid": "fendaf7rut9moc"
          },
          "editorMode": "code",
          "format": "table",
          "rawQuery": true,
          "rawSql": "select * from alarm_logs\r\norder by timestamp",
          "refId": "A",
          "sql": {
            "columns": [
              {
                "name": "COUNT",
                "parameters": [
                  {
                    "name": "",
                    "type": "functionParameter"
                  }
                ],
                "type": "function"
              }
            ],
            "groupBy": [
              {
                "property": {
                  "type": "string"
                },
                "type": "groupBy"
              }
            ],
            "limit": 50
          },
          "table": "alarm_logs"
        }
      ],
      "title": "DataBase",
      "type": "table"
    },
    {
      "datasource": {
        "type": "grafana-postgresql-datasource",
        "uid": "fendaf7rut9moc"
      },
      "fieldConfig": {
        "defaults": {
          "mappings": [],
          "thresholds": {
            "mode": "percentage",
            "steps": [
              {
                "color": "green"
              },
              {
                "color": "orange",
                "value": 70
              },
              {
                "color": "red",
                "value": 85
              }
            ]
          }
        },
        "overrides": []
      },
      "gridPos": {
        "h": 11,
        "w": 16,
        "x": 0,
        "y": 13
      },
      "id": 1,
      "options": {
        "minVizHeight": 75,
        "minVizWidth": 75,
        "orientation": "auto",
        "reduceOptions": {
          "calcs": [],
          "fields": "",
          "values": true
        },
        "showThresholdLabels": false,
        "showThresholdMarkers": true,
        "sizing": "auto"
      },
      "pluginVersion": "12.0.1",
      "targets": [
        {
          "datasource": {
            "type": "grafana-postgresql-datasource",
            "uid": "fendaf7rut9moc"
          },
          "editorMode": "code",
          "format": "table",
          "rawQuery": true,
          "rawSql": "SELECT state, COUNT(*) AS count  \r\nFROM alarm_logs  \r\nGROUP BY state  \r\nORDER BY count",
          "refId": "A",
          "sql": {
            "columns": [
              {
                "parameters": [],
                "type": "function"
              }
            ],
            "groupBy": [
              {
                "property": {
                  "type": "string"
                },
                "type": "groupBy"
              }
            ],
            "limit": 50
          },
          "table": "alarm_logs"
        }
      ],
      "title": "State count ",
      "type": "gauge"
    }
  ],
  "preload": false,
  "schemaVersion": 41,
  "tags": [],
  "templating": {
    "list": []
  },
  "time": {
    "from": "now-1m",
    "to": "now"
  },
  "timepicker": {},
  "timezone": "browser",
  "title": "Спидометр",
  "uid": "ea79d250-b1eb-4308-9627-0b18796f9276",
  "version": 9
}